PipelineTS/__init__.py
PipelineTS/dataset.py
PipelineTS/metrics.py
PipelineTS/base/___init__.py
PipelineTS/base/base.py
PipelineTS/base/base_utils.py
PipelineTS/base/darts_base.py
PipelineTS/base/spines_base.py
PipelineTS/io/__init__.py
PipelineTS/ml_model/__init__.py
PipelineTS/ml_model/gbdt.py
PipelineTS/ml_model/multi_output_model.py
PipelineTS/ml_model/wide_gbrt.py
PipelineTS/nn_model/__init__.py
PipelineTS/nn_model/d_linear.py
PipelineTS/nn_model/gau.py
PipelineTS/nn_model/n_beats.py
PipelineTS/nn_model/n_hits.py
PipelineTS/nn_model/n_linear.py
PipelineTS/nn_model/patch_rnn.py
PipelineTS/nn_model/stacking_rnn.py
PipelineTS/nn_model/tcn.py
PipelineTS/nn_model/tft.py
PipelineTS/nn_model/tide.py
PipelineTS/nn_model/time2vec.py
PipelineTS/nn_model/transformer.py
PipelineTS/pipeline/__init__.py
PipelineTS/pipeline/pipeline.py
PipelineTS/pipeline/pipeline_configs.py
PipelineTS/pipeline/pipeline_models.py
PipelineTS/plot/__init__.py
PipelineTS/preprocessing/__init__.py
PipelineTS/preprocessing/scalers.py
PipelineTS/spinesTS/__init__.py
PipelineTS/spinesTS/features_generator.py
PipelineTS/spinesTS/frame.py
PipelineTS/spinesTS/metrics.py
PipelineTS/spinesTS/pipeline.py
PipelineTS/spinesTS/base/__init__.py
PipelineTS/spinesTS/base/_base_mixin.py
PipelineTS/spinesTS/base/_torch_mixin.py
PipelineTS/spinesTS/data/__init__.py
PipelineTS/spinesTS/data/_data_generator.py
PipelineTS/spinesTS/data/_data_reader.py
PipelineTS/spinesTS/layers/__init__.py
PipelineTS/spinesTS/layers/_concat_layers.py
PipelineTS/spinesTS/layers/_decompose_layers.py
PipelineTS/spinesTS/layers/_enhance_layers.py
PipelineTS/spinesTS/layers/_multi_features.py
PipelineTS/spinesTS/layers/_position_encoder.py
PipelineTS/spinesTS/ml_model/__init__.py
PipelineTS/spinesTS/ml_model/_dummy_model.py
PipelineTS/spinesTS/ml_model/_gbrt.py
PipelineTS/spinesTS/ml_model/_io_model.py
PipelineTS/spinesTS/ml_model/_multistep_forecast.py
PipelineTS/spinesTS/nn/__init__.py
PipelineTS/spinesTS/nn/_gau.py
PipelineTS-0.3.12.dist-info/LICENSE
PipelineTS-0.3.12.dist-info/METADATA
PipelineTS-0.3.12.dist-info/WHEEL
PipelineTS-0.3.12.dist-info/top_level.txt
PipelineTS-0.3.12.dist-info/RECORD
