Metadata-Version: 2.1
Name: PipelineTS
Version: 0.3.12
Summary: One-stop time series analysis tool, supporting time series data preprocessing, feature engineering, model training, model evaluation, model prediction, etc. Based on spinesTS and darts.
Home-page: https://github.com/BirchKwok/PipelineTS
Author: Birch Kwok
Author-email: birchkwok@gmail.com
Keywords: time series forecasting
Classifier: Intended Audience :: Science/Research
Classifier: Intended Audience :: Developers
Classifier: Topic :: Software Development
Classifier: Topic :: Scientific/Engineering
Classifier: License :: OSI Approved :: Apache Software License
Classifier: Operating System :: OS Independent
Classifier: Programming Language :: Python :: 3.9
Classifier: Programming Language :: Python :: 3.10
Classifier: Programming Language :: Python :: 3.11
Requires-Python: >=3.9
License-File: LICENSE
Requires-Dist: matplotlib >=3.7.1
Requires-Dist: numpy >=1.24.3
Requires-Dist: pandas >=2.0.3
Requires-Dist: scikit-learn >=1.3.0
Requires-Dist: xgboost >=1.6.0
Requires-Dist: darts >=0.24.0
Requires-Dist: catboost >=1.2.2
Requires-Dist: lightgbm >=3.3.5
Requires-Dist: frozendict >=2.3.0
Requires-Dist: spinesUtils >=0.3.13
Requires-Dist: tabulate >=0.8.9
Requires-Dist: torch >=1.8.0
Requires-Dist: MAPIE >=0.7.0
Requires-Dist: cloudpickle >=2.2.1
Requires-Dist: scipy >=1.7.3
Provides-Extra: all
Requires-Dist: matplotlib >=3.7.1 ; extra == 'all'
Requires-Dist: numpy >=1.24.3 ; extra == 'all'
Requires-Dist: pandas >=2.0.3 ; extra == 'all'
Requires-Dist: scikit-learn >=1.3.0 ; extra == 'all'
Requires-Dist: xgboost >=1.6.0 ; extra == 'all'
Requires-Dist: darts >=0.24.0 ; extra == 'all'
Requires-Dist: catboost >=1.2.2 ; extra == 'all'
Requires-Dist: lightgbm >=3.3.5 ; extra == 'all'
Requires-Dist: frozendict >=2.3.0 ; extra == 'all'
Requires-Dist: spinesUtils >=0.3.13 ; extra == 'all'
Requires-Dist: tabulate >=0.8.9 ; extra == 'all'
Requires-Dist: torch >=1.8.0 ; extra == 'all'
Requires-Dist: MAPIE >=0.7.0 ; extra == 'all'
Requires-Dist: cloudpickle >=2.2.1 ; extra == 'all'
Requires-Dist: scipy >=1.7.3 ; extra == 'all'
Requires-Dist: prophet >=1.1.4 ; extra == 'all'
Provides-Extra: core
Requires-Dist: matplotlib >=3.7.1 ; extra == 'core'
Requires-Dist: numpy >=1.24.3 ; extra == 'core'
Requires-Dist: pandas >=2.0.3 ; extra == 'core'
Requires-Dist: scikit-learn >=1.3.0 ; extra == 'core'
Requires-Dist: xgboost >=1.6.0 ; extra == 'core'
Requires-Dist: darts >=0.24.0 ; extra == 'core'
Requires-Dist: catboost >=1.2.2 ; extra == 'core'
Requires-Dist: lightgbm >=3.3.5 ; extra == 'core'
Requires-Dist: frozendict >=2.3.0 ; extra == 'core'
Requires-Dist: spinesUtils >=0.3.13 ; extra == 'core'
Requires-Dist: tabulate >=0.8.9 ; extra == 'core'
Requires-Dist: torch >=1.8.0 ; extra == 'core'
Requires-Dist: MAPIE >=0.7.0 ; extra == 'core'
Requires-Dist: cloudpickle >=2.2.1 ; extra == 'core'
Requires-Dist: scipy >=1.7.3 ; extra == 'core'
